fsoe_master/__init__.py
fsoe_master/_version.py
fsoe_master/fsoe_master.cp312-win_amd64.pyd
fsoe_master-0.2.0.dist-info/LICENSE.md
fsoe_master-0.2.0.dist-info/METADATA
fsoe_master-0.2.0.dist-info/WHEEL
fsoe_master-0.2.0.dist-info/top_level.txt
fsoe_master-0.2.0.dist-info/RECORD
